nbzip/__init__.py
nbzip/handlers.py
nbzip/static/tree.js
nbzip-0.1.0.dist-info/DESCRIPTION.rst
nbzip-0.1.0.dist-info/METADATA
nbzip-0.1.0.dist-info/RECORD
nbzip-0.1.0.dist-info/WHEEL
nbzip-0.1.0.dist-info/metadata.json
nbzip-0.1.0.dist-info/top_level.txt
