Metadata-Version: 2.0
Name: nbzip
Version: 0.1.0
Summary: Compresses and downloads all files in any of the user's directories.
Home-page: https://github.com/data-8/nbzip
Author: Data 8 @ UC Berkeley
Author-email: peterkangveerman@berkeley.edu
License: UNKNOWN
Platform: UNKNOWN
Classifier: Development Status :: 4 - Beta
Classifier: License :: OSI Approved :: BSD License
Classifier: Operating System :: POSIX
Classifier: Operating System :: MacOS
Classifier: Operating System :: Unix
Classifier: Programming Language :: Python :: 3
Classifier: Topic :: Software Development :: Libraries :: Python Modules
Classifier: Framework :: Jupyter
Requires-Dist: notebook
Requires-Dist: pytest
